community_transformers-0.0.6.dist-info/DESCRIPTION.rst
community_transformers-0.0.6.dist-info/METADATA
community_transformers-0.0.6.dist-info/RECORD
community_transformers-0.0.6.dist-info/WHEEL
community_transformers-0.0.6.dist-info/metadata.json
community_transformers-0.0.6.dist-info/top_level.txt
transformers/__init__.py
transformers/t.py
